dash_mistletoe/__init__.py
dash_mistletoe/dash_renderer.py
dash_mistletoe-0.2.4.dist-info/LICENSE
dash_mistletoe-0.2.4.dist-info/METADATA
dash_mistletoe-0.2.4.dist-info/WHEEL
dash_mistletoe-0.2.4.dist-info/top_level.txt
dash_mistletoe-0.2.4.dist-info/RECORD
