Metadata-Version: 2.1
Name: dash-mistletoe
Version: 0.2.4
Summary: A wrapper of mistletoe to output Markdown as dash components
Home-page: https://github.com/bradley-erickson/dash-mistletoe
Author: Bradley Erickson
Author-email: bbwe24@gmail.com
License: MIT
Platform: UNKNOWN
Requires-Dist: dash (>=2.1.0)
Requires-Dist: mistletoe (==0.9.0)
